spy_spider/__init__.py
spy_spider/core/__init__.py
spy_spider/core/downloader.py
spy_spider/core/engine.py
spy_spider/core/scheduler.py
spy_spider/db/__init__.py
spy_spider/downloaders/__init__.py
spy_spider/entities/__init__.py
spy_spider/http/__init__.py
spy_spider/http/request.py
spy_spider/http/response.py
spy_spider/items/__init__.py
spy_spider/middlewares/__init__.py
spy_spider/models/__init__.py
spy_spider/settings/__init__.py
spy_spider/settings/default_settings.py
spy_spider/spiders/__init__.py
spy_spider/utils/__init__.py
spy_spider/utils/logger.py
spy_spider/utils/project.py
spy_spider/utils/spider_priority_queue.py
spy_spider/utils/tools.py
spy_spider-0.1.4.dist-info/METADATA
spy_spider-0.1.4.dist-info/WHEEL
spy_spider-0.1.4.dist-info/RECORD
